[
  {
    "Teacher": "Josef Nobach",
    "RoleInfo": "PROG1000X",
    "SecondaryInfo": "Teacher: Josef Nobach",
    "PersonType": 0,
    "Id": 1,
    "Name": "Fahad Khan",
    "PictureUrl": "C:\\Users\\Josef\\Documents\\Github\\SchoolOrganizer\\bin\\Debug\\net9.0\\Data\\ProfileImages\\Fahad Khan_20251030_204714.jpg",
    "OriginalImagePath": null,
    "ClassName": "PROG1000X",
    "Teachers": [
      "Josef Nobach"
    ],
    "Email": "fahad.khan@elev.ga.ntig.se",
    "EnrollmentDate": "2025-10-30T20:47:14.3911386",
    "CropSettings": null,
    "AssignmentRatings": {},
    "AssignmentNotes": {},
    "AssignmentNotesTimestamps": {},
    "AssignmentNotesSidebarWidths": {}
  },
  {
    "Teacher": "Josef Nobach",
    "RoleInfo": "PROG1000X",
    "SecondaryInfo": "Teacher: Josef Nobach",
    "PersonType": 0,
    "Id": 2,
    "Name": "Mohamed Ramo",
    "PictureUrl": "C:\\Users\\Josef\\Documents\\Github\\SchoolOrganizer\\bin\\Debug\\net9.0\\Data\\ProfileImages\\Mohamed Ramo_20251030_204714.jpg",
    "OriginalImagePath": null,
    "ClassName": "PROG1000X",
    "Teachers": [
      "Josef Nobach"
    ],
    "Email": "mohamed.ramo@elev.ga.ntig.se",
    "EnrollmentDate": "2025-10-30T20:47:14.4444625",
    "CropSettings": null,
    "AssignmentRatings": {},
    "AssignmentNotes": {},
    "AssignmentNotesTimestamps": {},
    "AssignmentNotesSidebarWidths": {}
  },
  {
    "Teacher": "Josef Nobach",
    "RoleInfo": "PROG1000X",
    "SecondaryInfo": "Teacher: Josef Nobach",
    "PersonType": 0,
    "Id": 3,
    "Name": "Abdullah Hamdan",
    "PictureUrl": "C:\\Users\\Josef\\Documents\\Github\\SchoolOrganizer\\bin\\Debug\\net9.0\\Data\\ProfileImages\\Abdullah Hamdan_20251030_204714.jpg",
    "OriginalImagePath": null,
    "ClassName": "PROG1000X",
    "Teachers": [
      "Josef Nobach"
    ],
    "Email": "abdullah.hamdan@elev.ga.ntig.se",
    "EnrollmentDate": "2025-10-30T20:47:14.4578788",
    "CropSettings": null,
    "AssignmentRatings": {},
    "AssignmentNotes": {},
    "AssignmentNotesTimestamps": {},
    "AssignmentNotesSidebarWidths": {}
  },
  {
    "Teacher": "Josef Nobach",
    "RoleInfo": "PROG1000X",
    "SecondaryInfo": "Teacher: Josef Nobach",
    "PersonType": 0,
    "Id": 4,
    "Name": "Ward Heidar",
    "PictureUrl": "C:\\Users\\Josef\\Documents\\Github\\SchoolOrganizer\\bin\\Debug\\net9.0\\Data\\ProfileImages\\Ward Heidar_20251030_204714.jpg",
    "OriginalImagePath": null,
    "ClassName": "PROG1000X",
    "Teachers": [
      "Josef Nobach"
    ],
    "Email": "ward.heidar@elev.ga.ntig.se",
    "EnrollmentDate": "2025-10-30T20:47:14.4723945",
    "CropSettings": null,
    "AssignmentRatings": {},
    "AssignmentNotes": {},
    "AssignmentNotesTimestamps": {},
    "AssignmentNotesSidebarWidths": {}
  },
  {
    "Teacher": "Josef Nobach",
    "RoleInfo": "PROG1000X",
    "SecondaryInfo": "Teacher: Josef Nobach",
    "PersonType": 0,
    "Id": 5,
    "Name": "Shaza Zaher",
    "PictureUrl": "C:\\Users\\Josef\\Documents\\Github\\SchoolOrganizer\\bin\\Debug\\net9.0\\Data\\ProfileImages\\Shaza Zaher_20251030_204714.jpg",
    "OriginalImagePath": null,
    "ClassName": "PROG1000X",
    "Teachers": [
      "Josef Nobach"
    ],
    "Email": "shaza.zaher@elev.ga.ntig.se",
    "EnrollmentDate": "2025-10-30T20:47:14.4880663",
    "CropSettings": null,
    "AssignmentRatings": {},
    "AssignmentNotes": {},
    "AssignmentNotesTimestamps": {},
    "AssignmentNotesSidebarWidths": {}
  },
  {
    "Teacher": "Josef Nobach",
    "RoleInfo": "PROG1000X",
    "SecondaryInfo": "Teacher: Josef Nobach",
    "PersonType": 0,
    "Id": 6,
    "Name": "Vildan Kapetanovic",
    "PictureUrl": "C:\\Users\\Josef\\Documents\\Github\\SchoolOrganizer\\bin\\Debug\\net9.0\\Data\\ProfileImages\\Vildan Kapetanovic_20251030_204714.jpg",
    "OriginalImagePath": null,
    "ClassName": "PROG1000X",
    "Teachers": [
      "Josef Nobach"
    ],
    "Email": "vildan.kapetanovic@elev.ga.ntig.se",
    "EnrollmentDate": "2025-10-30T20:47:14.5030091",
    "CropSettings": null,
    "AssignmentRatings": {},
    "AssignmentNotes": {},
    "AssignmentNotesTimestamps": {},
    "AssignmentNotesSidebarWidths": {}
  },
  {
    "Teacher": "Josef Nobach",
    "RoleInfo": "PROG1000X",
    "SecondaryInfo": "Teacher: Josef Nobach",
    "PersonType": 0,
    "Id": 7,
    "Name": "Lujain Shaar",
    "PictureUrl": "C:\\Users\\Josef\\Documents\\Github\\SchoolOrganizer\\bin\\Debug\\net9.0\\Data\\ProfileImages\\Lujain Shaar_20251030_204714.jpg",
    "OriginalImagePath": null,
    "ClassName": "PROG1000X",
    "Teachers": [
      "Josef Nobach"
    ],
    "Email": "lujain.shaar@elev.ga.ntig.se",
    "EnrollmentDate": "2025-10-30T20:47:14.5173261",
    "CropSettings": null,
    "AssignmentRatings": {},
    "AssignmentNotes": {},
    "AssignmentNotesTimestamps": {},
    "AssignmentNotesSidebarWidths": {}
  },
  {
    "Teacher": "Josef Nobach",
    "RoleInfo": "PROG1000X",
    "SecondaryInfo": "Teacher: Josef Nobach",
    "PersonType": 0,
    "Id": 8,
    "Name": "Oskar Hansson Berg",
    "PictureUrl": "C:\\Users\\Josef\\Documents\\Github\\SchoolOrganizer\\bin\\Debug\\net9.0\\Data/ProfileImages\\student_8_1761853790342.png",
    "OriginalImagePath": "C:\\Users\\Josef\\Documents\\Github\\SchoolOrganizer\\bin\\Debug\\net9.0\\Data/ProfileImages/Originals\\1761853709478_505409302_3570326839929971_6733760168561066981_n.jpg",
    "ClassName": "PROG1000X",
    "Teachers": [
      "Josef Nobach"
    ],
    "Email": "oskar.hanssonberg@elev.ga.ntig.se",
    "EnrollmentDate": "2025-10-30T20:47:14.5304982",
    "CropSettings": "{\u0022X\u0022:212.67741935483866,\u0022Y\u0022:41.860215053763454,\u0022Width\u0022:665.6129032258065,\u0022Height\u0022:665.6129032258065,\u0022RotationAngle\u0022:0,\u0022ImageDisplayWidth\u0022:700.6451612903227,\u0022ImageDisplayHeight\u0022:965.3333333333334,\u0022ImageDisplayOffsetX\u0022:212.67741935483866,\u0022ImageDisplayOffsetY\u0022:0}",
    "AssignmentRatings": {},
    "AssignmentNotes": {},
    "AssignmentNotesTimestamps": {},
    "AssignmentNotesSidebarWidths": {}
  },
  {
    "Teacher": "Josef Nobach",
    "RoleInfo": "PROG1000X",
    "SecondaryInfo": "Teacher: Josef Nobach",
    "PersonType": 0,
    "Id": 9,
    "Name": "Mohammad Masri",
    "PictureUrl": "C:\\Users\\Josef\\Documents\\Github\\SchoolOrganizer\\bin\\Debug\\net9.0\\Data\\ProfileImages\\Mohammad Masri_20251030_204714.jpg",
    "OriginalImagePath": null,
    "ClassName": "PROG1000X",
    "Teachers": [
      "Josef Nobach"
    ],
    "Email": "mohammad.masri@elev.ga.ntig.se",
    "EnrollmentDate": "2025-10-30T20:47:14.5451847",
    "CropSettings": null,
    "AssignmentRatings": {},
    "AssignmentNotes": {},
    "AssignmentNotesTimestamps": {},
    "AssignmentNotesSidebarWidths": {}
  },
  {
    "Teacher": "Josef Nobach",
    "RoleInfo": "PROG1000X",
    "SecondaryInfo": "Teacher: Josef Nobach",
    "PersonType": 0,
    "Id": 10,
    "Name": "Neithan Jakobsen",
    "PictureUrl": "C:\\Users\\Josef\\Documents\\Github\\SchoolOrganizer\\bin\\Debug\\net9.0\\Data\\ProfileImages\\Neithan Jakobsen_20251030_204714.jpg",
    "OriginalImagePath": null,
    "ClassName": "PROG1000X",
    "Teachers": [
      "Josef Nobach"
    ],
    "Email": "neithan.jakobsen@elev.ga.ntig.se",
    "EnrollmentDate": "2025-10-30T20:47:14.5999338",
    "CropSettings": null,
    "AssignmentRatings": {},
    "AssignmentNotes": {},
    "AssignmentNotesTimestamps": {},
    "AssignmentNotesSidebarWidths": {}
  },
  {
    "Teacher": "Josef Nobach",
    "RoleInfo": "PROG1000X",
    "SecondaryInfo": "Teacher: Josef Nobach",
    "PersonType": 0,
    "Id": 11,
    "Name": "Hadil Tlas",
    "PictureUrl": "C:\\Users\\Josef\\Documents\\Github\\SchoolOrganizer\\bin\\Debug\\net9.0\\Data\\ProfileImages\\Hadil Tlas_20251030_204714.jpg",
    "OriginalImagePath": null,
    "ClassName": "PROG1000X",
    "Teachers": [
      "Josef Nobach"
    ],
    "Email": "hadil.tlas@elev.ga.ntig.se",
    "EnrollmentDate": "2025-10-30T20:47:14.6132373",
    "CropSettings": null,
    "AssignmentRatings": {},
    "AssignmentNotes": {},
    "AssignmentNotesTimestamps": {},
    "AssignmentNotesSidebarWidths": {}
  },
  {
    "Teacher": "Josef Nobach",
    "RoleInfo": "PROG1000X",
    "SecondaryInfo": "Teacher: Josef Nobach",
    "PersonType": 0,
    "Id": 12,
    "Name": "Dante Sj\u00F6vall Fridh",
    "PictureUrl": "C:\\Users\\Josef\\Documents\\Github\\SchoolOrganizer\\bin\\Debug\\net9.0\\Data\\ProfileImages\\Dante Sj\u00F6vall Fridh_20251030_204714.jpg",
    "OriginalImagePath": null,
    "ClassName": "PROG1000X",
    "Teachers": [
      "Josef Nobach"
    ],
    "Email": "dante.sjovallfridh@elev.ga.ntig.se",
    "EnrollmentDate": "2025-10-30T20:47:14.6260342",
    "CropSettings": null,
    "AssignmentRatings": {},
    "AssignmentNotes": {},
    "AssignmentNotesTimestamps": {},
    "AssignmentNotesSidebarWidths": {}
  },
  {
    "Teacher": "Josef Nobach",
    "RoleInfo": "PROG1000X",
    "SecondaryInfo": "Teacher: Josef Nobach",
    "PersonType": 0,
    "Id": 13,
    "Name": "Emil Aspenberg",
    "PictureUrl": "C:\\Users\\Josef\\Documents\\Github\\SchoolOrganizer\\bin\\Debug\\net9.0\\Data\\ProfileImages\\Emil Aspenberg_20251030_204714.jpg",
    "OriginalImagePath": null,
    "ClassName": "PROG1000X",
    "Teachers": [
      "Josef Nobach"
    ],
    "Email": "emil.aspenberg@elev.ga.ntig.se",
    "EnrollmentDate": "2025-10-30T20:47:14.6397457",
    "CropSettings": null,
    "AssignmentRatings": {},
    "AssignmentNotes": {},
    "AssignmentNotesTimestamps": {},
    "AssignmentNotesSidebarWidths": {}
  },
  {
    "Teacher": "Josef Nobach",
    "RoleInfo": "PROG1000X",
    "SecondaryInfo": "Teacher: Josef Nobach",
    "PersonType": 0,
    "Id": 14,
    "Name": "Sixten \u00C5berg",
    "PictureUrl": "C:\\Users\\Josef\\Documents\\Github\\SchoolOrganizer\\bin\\Debug\\net9.0\\Data\\ProfileImages\\Sixten \u00C5berg_20251030_204714.jpg",
    "OriginalImagePath": null,
    "ClassName": "PROG1000X",
    "Teachers": [
      "Josef Nobach"
    ],
    "Email": "sixten.aberg@elev.ga.ntig.se",
    "EnrollmentDate": "2025-10-30T20:47:14.6522808",
    "CropSettings": null,
    "AssignmentRatings": {},
    "AssignmentNotes": {},
    "AssignmentNotesTimestamps": {},
    "AssignmentNotesSidebarWidths": {}
  },
  {
    "Teacher": "Josef Nobach",
    "RoleInfo": "PROG1000X",
    "SecondaryInfo": "Teacher: Josef Nobach",
    "PersonType": 0,
    "Id": 15,
    "Name": "Oliver Wikstr\u00F6m",
    "PictureUrl": "C:\\Users\\Josef\\Documents\\Github\\SchoolOrganizer\\bin\\Debug\\net9.0\\Data\\ProfileImages\\Oliver Wikstr\u00F6m_20251030_204714.jpg",
    "OriginalImagePath": null,
    "ClassName": "PROG1000X",
    "Teachers": [
      "Josef Nobach"
    ],
    "Email": "oliver.wikstrom@elev.ga.ntig.se",
    "EnrollmentDate": "2025-10-30T20:47:14.6805759",
    "CropSettings": null,
    "AssignmentRatings": {},
    "AssignmentNotes": {},
    "AssignmentNotesTimestamps": {},
    "AssignmentNotesSidebarWidths": {}
  },
  {
    "Teacher": "Josef Nobach",
    "RoleInfo": "PROG1000X",
    "SecondaryInfo": "Teacher: Josef Nobach",
    "PersonType": 0,
    "Id": 16,
    "Name": "Mathias Andersson",
    "PictureUrl": "C:\\Users\\Josef\\Documents\\Github\\SchoolOrganizer\\bin\\Debug\\net9.0\\Data\\ProfileImages\\Mathias Andersson_20251030_204714.jpg",
    "OriginalImagePath": null,
    "ClassName": "PROG1000X",
    "Teachers": [
      "Josef Nobach"
    ],
    "Email": "mathias.andersson@elev.ga.ntig.se",
    "EnrollmentDate": "2025-10-30T20:47:14.6971737",
    "CropSettings": null,
    "AssignmentRatings": {},
    "AssignmentNotes": {},
    "AssignmentNotesTimestamps": {},
    "AssignmentNotesSidebarWidths": {}
  },
  {
    "Teacher": "Josef Nobach",
    "RoleInfo": "PROG1000X",
    "SecondaryInfo": "Teacher: Josef Nobach",
    "PersonType": 0,
    "Id": 17,
    "Name": "Majd Alshehadat",
    "PictureUrl": "C:\\Users\\Josef\\Documents\\Github\\SchoolOrganizer\\bin\\Debug\\net9.0\\Data\\ProfileImages\\Majd Alshehadat_20251030_204714.jpg",
    "OriginalImagePath": null,
    "ClassName": "PROG1000X",
    "Teachers": [
      "Josef Nobach"
    ],
    "Email": "majdaldin.alshehadat@elev.ga.ntig.se",
    "EnrollmentDate": "2025-10-30T20:47:14.7100902",
    "CropSettings": null,
    "AssignmentRatings": {},
    "AssignmentNotes": {},
    "AssignmentNotesTimestamps": {},
    "AssignmentNotesSidebarWidths": {}
  },
  {
    "Teacher": "Josef Nobach",
    "RoleInfo": "PROG1000X",
    "SecondaryInfo": "Teacher: Josef Nobach",
    "PersonType": 0,
    "Id": 18,
    "Name": "Filip H\u00E5kansson",
    "PictureUrl": "C:\\Users\\Josef\\Documents\\Github\\SchoolOrganizer\\bin\\Debug\\net9.0\\Data\\ProfileImages\\Filip H\u00E5kansson_20251030_204714.jpg",
    "OriginalImagePath": null,
    "ClassName": "PROG1000X",
    "Teachers": [
      "Josef Nobach"
    ],
    "Email": "filip.hakansson@elev.ga.ntig.se",
    "EnrollmentDate": "2025-10-30T20:47:14.7229734",
    "CropSettings": null,
    "AssignmentRatings": {},
    "AssignmentNotes": {},
    "AssignmentNotesTimestamps": {},
    "AssignmentNotesSidebarWidths": {}
  },
  {
    "Teacher": "Josef Nobach",
    "RoleInfo": "PROG1000X",
    "SecondaryInfo": "Teacher: Josef Nobach",
    "PersonType": 0,
    "Id": 19,
    "Name": "Milo Sandengrip",
    "PictureUrl": "C:\\Users\\Josef\\Documents\\Github\\SchoolOrganizer\\bin\\Debug\\net9.0\\Data\\ProfileImages\\Milo Sandengrip_20251030_204714.jpg",
    "OriginalImagePath": null,
    "ClassName": "PROG1000X",
    "Teachers": [
      "Josef Nobach"
    ],
    "Email": "milo.sandengrip@elev.ga.ntig.se",
    "EnrollmentDate": "2025-10-30T20:47:14.7357658",
    "CropSettings": null,
    "AssignmentRatings": {},
    "AssignmentNotes": {},
    "AssignmentNotesTimestamps": {},
    "AssignmentNotesSidebarWidths": {}
  },
  {
    "Teacher": "Josef Nobach",
    "RoleInfo": "PROG1000X",
    "SecondaryInfo": "Teacher: Josef Nobach",
    "PersonType": 0,
    "Id": 20,
    "Name": "Gunnar Nord",
    "PictureUrl": "C:\\Users\\Josef\\Documents\\Github\\SchoolOrganizer\\bin\\Debug\\net9.0\\Data\\ProfileImages\\Gunnar Nord_20251030_204714.jpg",
    "OriginalImagePath": null,
    "ClassName": "PROG1000X",
    "Teachers": [
      "Josef Nobach"
    ],
    "Email": "gunnar.nord@elev.ga.ntig.se",
    "EnrollmentDate": "2025-10-30T20:47:14.7490978",
    "CropSettings": null,
    "AssignmentRatings": {},
    "AssignmentNotes": {},
    "AssignmentNotesTimestamps": {},
    "AssignmentNotesSidebarWidths": {}
  }
]